arguable/__init__.py
arguable/base.py
arguable/parser.py
arguable/utils.py
arguable-1.0.dist-info/LICENSE
arguable-1.0.dist-info/WHEEL
arguable-1.0.dist-info/METADATA
arguable-1.0.dist-info/RECORD
