Metadata-Version: 2.1
Name: arguable
Version: 1.0
Summary: class-level configuration via argparse
Home-page: https://github.com/Dominik1123/arguable
License: MIT
Keywords: argparse,configuration
Author: Dominik1123
Author-email: 15989985+Dominik1123@users.noreply.github.com
Requires-Python: >=3.7,<4.0
Classifier: License :: OSI Approved :: MIT License
Classifier: Programming Language :: Python :: 3
Classifier: Programming Language :: Python :: 3.7
Classifier: Programming Language :: Python :: 3.8
Requires-Dist: importlib_metadata (>=1.6.1,<2.0.0); python_version < "3.8"
Project-URL: Repository, https://github.com/Dominik1123/arguable
